uv_glci_bump_version/__init__.py
uv_glci_bump_version/__main__.py
uv_glci_bump_version/app.py
uv_glci_bump_version/util.py
uv_glci_bump_version/version.py
uv_glci_bump_version-0.8.6.dist-info/METADATA
uv_glci_bump_version-0.8.6.dist-info/WHEEL
uv_glci_bump_version-0.8.6.dist-info/entry_points.txt
uv_glci_bump_version-0.8.6.dist-info/RECORD
