Metadata-Version: 2.4
Name: uv-glci-bump-version
Version: 0.8.6
Summary: Add your description here
Author-email: Florian Daude <floriandaude@hotmail.fr>
Requires-Python: >=3.13
Requires-Dist: cyclopts>=3.11.1
Requires-Dist: tomlkit>=0.13.2
